{
    "type": "FeatureCollection",
    "features": [
      {
        "type": "Feature",
        "properties": {
          "name": "儋州市"
        },
        "geometry": {
          "type": "Polygon",
          "coordinates": [
            [
              [
                829.2315673828125,
                19.751840567078425
              ],
              [
                829.2281341552734,
                19.727927643457424
              ],
              [
                829.2315673828125,
                19.70982899738849
              ],
              [
                829.237060546875,
                19.680737597005137
              ],
              [
                829.2645263671875,
                19.658753923004706
              ],
              [
                829.2871856689453,
                19.630946725663854
              ],
              [
                829.3153381347656,
                19.611543503814232
              ],
              [
                829.3400573730468,
                19.58437505982636
              ],
              [
                829.3723297119141,
                19.55849608929051
              ],
              [
                829.3894958496094,
                19.541672530926927
              ],
              [
                829.4245147705078,
                19.52031702794756
              ],
              [
                829.4499206542969,
                19.497016896955444
              ],
              [
                829.4766998291014,
                19.480186937661344
              ],
              [
                829.5055389404297,
                19.46400263520258
              ],
              [
                829.5281982421875,
                19.44846418467642
              ],
              [
                829.5426177978514,
                19.421915889653373
              ],
              [
                829.5838165283203,
                19.412849624405244
              ],
              [
                829.610595703125,
                19.41803040932666
              ],
              [
                829.6373748779296,
                19.427096385573407
              ],
              [
                829.6463012695312,
                19.44134189745716
              ],
              [
                829.6483612060547,
                19.454291278067455
              ],
              [
                829.6497344970703,
                19.465297438875965
              ],
              [
                829.6559143066405,
                19.48860213599771
              ],
              [
                829.6593475341797,
                19.50996182862563
              ],
              [
                829.6710205078125,
                19.53261296541841
              ],
              [
                829.6854400634766,
                19.54490796683428
              ],
              [
                829.6895599365234,
                19.55914311419191
              ],
              [
                829.6943664550781,
                19.575964850253825
              ],
              [
                829.7074127197266,
                19.597959855171077
              ],
              [
                829.70947265625,
                19.61413073539383
              ],
              [
                829.7101593017578,
                19.638060653265285
              ],
              [
                829.7108459472655,
                19.657460671831295
              ],
              [
                829.7122192382812,
                19.669746136891607
              ],
              [
                829.7142791748047,
                19.674918682626934
              ],
              [
                829.7149658203125,
                19.687849316424483
              ],
              [
                829.7032928466796,
                19.693021277630717
              ],
              [
                829.6923065185547,
                19.693667761033677
              ],
              [
                829.6820068359374,
                19.704657579362323
              ],
              [
                829.6778869628906,
                19.71370745117832
              ],
              [
                829.6737670898438,
                19.732451984739097
              ],
              [
                829.6669006347656,
                19.74990181481406
              ],
              [
                829.6593475341797,
                19.758949123832704
              ],
              [
                829.6627807617188,
                19.7705806242426
              ],
              [
                829.6586608886719,
                19.783503518198092
              ],
              [
                829.6421813964844,
                19.784795749944877
              ],
              [
                829.6270751953125,
                19.790610663059088
              ],
              [
                829.610595703125,
                19.805470031696267
              ],
              [
                829.599609375,
                19.82291186759323
              ],
              [
                829.5858764648438,
                19.83970590082983
              ],
              [
                829.5652770996094,
                19.85003980790673
              ],
              [
                829.5604705810547,
                19.85003980790673
              ],
              [
                829.5515441894531,
                19.85003980790673
              ],
              [
                829.5433044433594,
                19.845518806331246
              ],
              [
                829.5357513427734,
                19.841643559642943
              ],
              [
                829.5316314697266,
                19.84099767599906
              ],
              [
                829.5357513427734,
                19.84810225157064
              ],
              [
                829.53369140625,
                19.853914849615904
              ],
              [
                829.5357513427734,
                19.864247831495575
              ],
              [
                829.5309448242188,
                19.861018846962747
              ],
              [
                829.5275115966797,
                19.85520650915748
              ],
              [
                829.5206451416016,
                19.84810225157064
              ],
              [
                829.5137786865233,
                19.843581194810728
              ],
              [
                829.5021057128906,
                19.84228944065956
              ],
              [
                829.4945526123047,
                19.841643559642943
              ],
              [
                829.4828796386719,
                19.837768218373313
              ],
              [
                829.478759765625,
                19.831309106118404
              ],
              [
                829.4725799560547,
                19.841643559642943
              ],
              [
                829.4691467285155,
                19.85003980790673
              ],
              [
                829.4657135009766,
                19.859727234743332
              ],
              [
                829.4588470458984,
                19.86876829938972
              ],
              [
                829.4540405273438,
                19.866830971786623
              ],
              [
                829.4526672363281,
                19.861018846962747
              ],
              [
                829.4471740722656,
                19.864893620513147
              ],
              [
                829.4478607177733,
                19.87005983797396
              ],
              [
                829.4403076171875,
                19.872642883577086
              ],
              [
                829.4368743896484,
                19.869414069997006
              ],
              [
                829.4313812255859,
                19.8616646491284
              ],
              [
                829.4224548339844,
                19.860373042167716
              ],
              [
                829.4114685058594,
                19.8616646491284
              ],
              [
                829.4039154052734,
                19.86876829938972
              ],
              [
                829.3956756591797,
                19.876517373059805
              ],
              [
                829.3901824951171,
                19.880391767822505
              ],
              [
                829.3853759765625,
                19.88620318233281
              ],
              [
                829.3798828125,
                19.880391767822505
              ],
              [
                829.3750762939453,
                19.88555748013722
              ],
              [
                829.3702697753906,
                19.89072302399691
              ],
              [
                829.3599700927734,
                19.89007734022808
              ],
              [
                829.3476104736328,
                19.88749457882739
              ],
              [
                829.3386840820312,
                19.882974645034466
              ],
              [
                829.3283843994141,
                19.884266067849776
              ],
              [
                829.3242645263671,
                19.88749457882739
              ],
              [
                829.3194580078125,
                19.892660059507026
              ],
              [
                829.3180847167969,
                19.89782537168145
              ],
              [
                829.3270111083983,
                19.905573023916027
              ],
              [
                829.3263244628906,
                19.909446707787783
              ],
              [
                829.3215179443358,
                19.91267470522604
              ],
              [
                829.3132781982422,
                19.913965885756145
              ],
              [
                829.3022918701172,
                19.91654821519283
              ],
              [
                829.295425415039,
                19.91332029680868
              ],
              [
                829.2885589599609,
                19.915257055745258
              ],
              [
                829.2892456054688,
                19.9075098777073
              ],
              [
                829.2885589599609,
                19.895242736659668
              ],
              [
                829.2816925048828,
                19.9004079645678
              ],
              [
                829.2645263671875,
                19.899762320296663
              ],
              [
                829.2638397216796,
                19.888140273126222
              ],
              [
                829.2562866210938,
                19.87458014015748
              ],
              [
                829.259033203125,
                19.866830971786623
              ],
              [
                829.2473602294922,
                19.8590814246897
              ],
              [
                829.2343139648438,
                19.85520650915748
              ],
              [
                829.2192077636718,
                19.85326901590216
              ],
              [
                829.2089080810547,
                19.840351789728015
              ],
              [
                829.2054748535156,
                19.826787571281773
              ],
              [
                829.1986083984375,
                19.828079451507104
              ],
              [
                829.1869354248047,
                19.826141627230633
              ],
              [
                829.1738891601562,
                19.816452151438234
              ],
              [
                829.1635894775391,
                19.803531931857556
              ],
              [
                829.1574096679688,
                19.78931847849429
              ],
              [
                829.1567230224609,
                19.78285739839342
              ],
              [
                829.1615295410156,
                19.774457602469948
              ],
              [
                829.1629028320312,
                19.764764980097123
              ],
              [
                829.1677093505859,
                19.755071768505005
              ],
              [
                829.1766357421875,
                19.73826880666261
              ],
              [
                829.1725158691406,
                19.733098308747795
              ],
              [
                829.1608428955078,
                19.726634950986693
              ],
              [
                829.149169921875,
                19.72340317405694
              ],
              [
                829.1526031494141,
                19.704657579362323
              ],
              [
                829.1649627685547,
                19.70918257927878
              ],
              [
                829.1732025146484,
                19.715646642797445
              ],
              [
                829.1807556152344,
                19.72340317405694
              ],
              [
                829.1841888427734,
                19.727281298529363
              ],
              [
                829.1917419433594,
                19.730512997022263
              ],
              [
                829.1972351074219,
                19.727281298529363
              ],
              [
                829.2061614990234,
                19.720817705457684
              ],
              [
                829.2137145996093,
                19.731805658115228
              ],
              [
                829.2226409912109,
                19.737622503577864
              ],
              [
                829.2315673828125,
                19.751840567078425
              ]
            ]
          ]
        }
      }
    ]
  }